{
  "project_info": {
    "project_number": "296057909486",
    "firebase_url": "https://argument-e0e00.firebaseio.com",
    "project_id": "argument-e0e00",
    "storage_bucket": "argument-e0e00.appspot.com"
  },
  "client": [
    {
      "client_info": {
        "mobilesdk_app_id": "1:296057909486:android:f35b44061780126e9ac3ff",
        "android_client_info": {
          "package_name": "br.com.argument"
        }
      },
      "oauth_client": [
        {
          "client_id": "296057909486-12jd9fs04r10uon31mc4egjj14h0csoo.apps.googleusercontent.com",
          "client_type": 3
        }
      ],
      "api_key": [
        {
          "current_key": "AIzaSyCVTqyY5E1H-NzYWbNFGyjtBNESUQYp8vc"
        }
      ],
      "services": {
        "appinvite_service": {
          "other_platform_oauth_client": [
            {
              "client_id": "296057909486-12jd9fs04r10uon31mc4egjj14h0csoo.apps.googleusercontent.com",
              "client_type": 3
            }
          ]
        }
      }
    }
  ],
  "configuration_version": "1"
}